[
  {
    "name": "facebook",
    "src": "/assets/icons/facebook.svg",
    "width": 10,
    "height": 19,
    "link": "#"
  },
  {
    "name": "twitter",
    "src": "/assets/icons/twitter.svg",
    "width": 18,
    "height": 15,
    "link": "#"
  },
  {
    "name": "youtube",
    "src": "/assets/icons/youtube.svg",
    "width": 20,
    "height": 14,
    "link": "#"
  },
  {
    "name": "linkedin",
    "src": "/assets/icons/linkedin.svg",
    "width": 18,
    "height": 16,
    "link": "#"
  },
  {
    "name": "discord",
    "src": "/assets/icons/discord.svg",
    "width": 21,
    "height": 16,
    "link": "#"
  }
]
